bitsv/__init__.py
bitsv/base58.py
bitsv/cli.py
bitsv/constants.py
bitsv/crypto.py
bitsv/curve.py
bitsv/exceptions.py
bitsv/format.py
bitsv/keygen.py
bitsv/op_return.py
bitsv/transaction.py
bitsv/utils.py
bitsv/wallet.py
bitsv/network/__init__.py
bitsv/network/fees.py
bitsv/network/meta.py
bitsv/network/rates.py
bitsv/network/transaction.py
bitsv/network/services/__init__.py
bitsv/network/services/bsvbookguarda.py
bitsv/network/services/fullnode.py
bitsv/network/services/mattercloud.py
bitsv/network/services/network.py
bitsv/network/services/standardrpcmethods.py
bitsv/network/services/whatsonchain.py
tests/__init__.py
tests/samples.py
tests/test_base58.py
tests/test_curve.py
tests/test_format.py
tests/test_transaction.py
tests/test_utils.py
tests/test_wallet.py
tests/utils.py
tests/network/__init__.py
tests/network/test_fees.py
tests/network/test_meta.py
tests/network/test_rates.py
tests/network/test_services.py
tests/network/test_transaction.py
bitsv-0.11.5.dist-info/AUTHORS.rst
bitsv-0.11.5.dist-info/LICENSE.txt
bitsv-0.11.5.dist-info/METADATA
bitsv-0.11.5.dist-info/WHEEL
bitsv-0.11.5.dist-info/entry_points.txt
bitsv-0.11.5.dist-info/top_level.txt
bitsv-0.11.5.dist-info/RECORD
