Metadata-Version: 2.1
Name: bitsv
Version: 0.11.5
Summary: Bitcoin SV made easier.
Home-page: https://github.com/AustEcon/bitsv
Author: AustEcon
Author-email: AustEcon0922@gmail.com
Maintainer: AustEcon
Maintainer-email: AustEcon0922@gmail.com
License: MIT
Download-URL: https://github.com/AustEcon/bitsv/tarball/0.11.5
Keywords: bitcoinsv,bsv,bitcoin sv,cryptocurrency,payments,tools,wallet
Platform: UNKNOWN
Classifier: Development Status :: 4 - Beta
Classifier: Intended Audience :: Developers
Classifier: Intended Audience :: End Users/Desktop
Classifier: License :: OSI Approved :: MIT License
Classifier: Natural Language :: English
Classifier: Operating System :: OS Independent
Classifier: Programming Language :: Python :: 3.5
Classifier: Programming Language :: Python :: 3.6
Classifier: Programming Language :: Python :: 3.7
Classifier: Programming Language :: Python :: 3.8
Classifier: Programming Language :: Python :: 3.9
Classifier: Programming Language :: Python :: Implementation :: CPython
Classifier: Programming Language :: Python :: Implementation :: PyPy
Requires-Dist: coincurve (>=4.3.0)
Requires-Dist: requests
Requires-Dist: python-bitcoinrpc
Requires-Dist: whatsonchain
Provides-Extra: cache
Requires-Dist: lmdb ; extra == 'cache'
Provides-Extra: cli
Requires-Dist: appdirs ; extra == 'cli'
Requires-Dist: click ; extra == 'cli'
Requires-Dist: privy ; extra == 'cli'
Requires-Dist: tinydb ; extra == 'cli'
